odoo/addons/product_supplierinfo_import_by_barcode_margin/README.rst
odoo/addons/product_supplierinfo_import_by_barcode_margin/__init__.py
odoo/addons/product_supplierinfo_import_by_barcode_margin/__manifest__.py
odoo/addons/product_supplierinfo_import_by_barcode_margin/i18n/it.po
odoo/addons/product_supplierinfo_import_by_barcode_margin/i18n/product_supplierinfo_import_by_barcode_margin.pot
odoo/addons/product_supplierinfo_import_by_barcode_margin/readme/CONTRIBUTORS.md
odoo/addons/product_supplierinfo_import_by_barcode_margin/readme/DESCRIPTION.md
odoo/addons/product_supplierinfo_import_by_barcode_margin/readme/USAGE.md
odoo/addons/product_supplierinfo_import_by_barcode_margin/security/ir.model.access.csv
odoo/addons/product_supplierinfo_import_by_barcode_margin/static/description/icon.png
odoo/addons/product_supplierinfo_import_by_barcode_margin/static/description/index.html
odoo/addons/product_supplierinfo_import_by_barcode_margin/wizards/__init__.py
odoo/addons/product_supplierinfo_import_by_barcode_margin/wizards/product_supplierinfo_import.py
odoo/addons/product_supplierinfo_import_by_barcode_margin/wizards/product_supplierinfo_import_views.xml
odoo_addon_product_supplierinfo_import_by_barcode_margin-16.0.1.0.0.4.dist-info/METADATA
odoo_addon_product_supplierinfo_import_by_barcode_margin-16.0.1.0.0.4.dist-info/WHEEL
odoo_addon_product_supplierinfo_import_by_barcode_margin-16.0.1.0.0.4.dist-info/top_level.txt
odoo_addon_product_supplierinfo_import_by_barcode_margin-16.0.1.0.0.4.dist-info/RECORD
