Metadata-Version: 2.1
Name: odoo-addon-product_supplierinfo_import_by_barcode_margin
Version: 16.0.1.0.0.4
Summary: Import supplier pricelists by barcode and margins
Home-page: https://github.com/OCA/product-attribute
Author: Tecnativa, Odoo Community Association (OCA)
Author-email: support@odoo-community.org
License: AGPL-3
Classifier: Programming Language :: Python
Classifier: Framework :: Odoo
Classifier: Framework :: Odoo :: 16.0
Classifier: License :: OSI Approved :: GNU Affero General Public License v3
Requires-Python: >=3.10
Requires-Dist: odoo-addon-product-pricelist-supplierinfo<16.1dev,>=16.0dev
Requires-Dist: odoo-addon-product-supplierinfo-import-by-barcode<16.1dev,>=16.0dev
Requires-Dist: odoo<16.1dev,>=16.0a
